simplegp/SKLearnInterface.py
simplegp/__init__.py
simplegp/Evolution/Evolution.py
simplegp/Evolution/__init__.py
simplegp/Fitness/FitnessFunction.py
simplegp/Fitness/__init__.py
simplegp/Nodes/BaseNode.py
simplegp/Nodes/SymbolicRegressionNodes.py
simplegp/Nodes/__init__.py
simplegp/Selection/Selection.py
simplegp/Selection/__init__.py
simplegp/Variation/Variation.py
simplegp/Variation/__init__.py
SimpleGP-1.0.1.dist-info/LICENSE.txt
SimpleGP-1.0.1.dist-info/METADATA
SimpleGP-1.0.1.dist-info/WHEEL
SimpleGP-1.0.1.dist-info/top_level.txt
SimpleGP-1.0.1.dist-info/RECORD
