Metadata-Version: 2.1
Name: SimpleGP
Version: 1.0.1
Summary: UNKNOWN
Home-page: https://github.com/marcovirgolin/SimpleGP
Author: Marco Virgolin
Author-email: marco.virgolin@gmail.com
License: UNKNOWN
Platform: UNKNOWN
Classifier: Programming Language :: Python :: 3
Classifier: License :: OSI Approved :: MIT License
Classifier: Operating System :: OS Independent
Requires-Python: >=3.7
License-File: LICENSE.txt
Requires-Dist: numpy (>=1.16.1)
Requires-Dist: scikit-learn (>=0.20.0)
